MANIFEST.in
README.md
setup.py
anthill/report/__init__.py
anthill/report/admin.py
anthill/report/handler.py
anthill/report/options.py
anthill/report/server.py
anthill/report/model/__init__.py
anthill/report/model/report.py
anthill/report/sql/reports.sql
anthill_report.egg-info/PKG-INFO
anthill_report.egg-info/SOURCES.txt
anthill_report.egg-info/dependency_links.txt
anthill_report.egg-info/namespace_packages.txt
anthill_report.egg-info/not-zip-safe
anthill_report.egg-info/requires.txt
anthill_report.egg-info/top_level.txt