Metadata-Version: 1.0
Name: anthill-report
Version: 0.2
Summary: User submitted reports collecting service
Home-page: https://github.com/anthill-platform/anthill-report
Author: desertkun
Author-email: desertkun@gmail.com
License: MIT
Platform: UNKNOWN
